__init__.py
factory_only.py
factory_only-0.1.dist-info/LICENSE
factory_only-0.1.dist-info/METADATA
factory_only-0.1.dist-info/WHEEL
factory_only-0.1.dist-info/top_level.txt
factory_only-0.1.dist-info/RECORD
